distil_trainer/__init__.py
distil_trainer/core/__init__.py
distil_trainer/core/callbacks.py
distil_trainer/core/config.py
distil_trainer/core/embedding_trainer.py
distil_trainer/core/hidden_state_trainer.py
distil_trainer/core/trainer.py
distil_trainer/data/__init__.py
distil_trainer/data/collators.py
distil_trainer/data/datamodule.py
distil_trainer/data/datasets.py
distil_trainer/data/embeddings_generator.py
distil_trainer/data/loaders.py
distil_trainer/data/ollama_embeddings_generator.py
distil_trainer/distillation/__init__.py
distil_trainer/distillation/losses.py
distil_trainer/distillation/multilingual.py
distil_trainer/distillation/strategies.py
distil_trainer/evaluation/__init__.py
distil_trainer/evaluation/benchmarks.py
distil_trainer/evaluation/evaluators.py
distil_trainer/evaluation/metrics.py
distil_trainer/pruning/__init__.py
distil_trainer/pruning/combined_pruning.py
distil_trainer/pruning/depth_pruning.py
distil_trainer/pruning/importance.py
distil_trainer/pruning/width_pruning.py
distil_trainer-0.1.27.dist-info/METADATA
distil_trainer-0.1.27.dist-info/WHEEL
distil_trainer-0.1.27.dist-info/licenses/LICENSE
distil_trainer-0.1.27.dist-info/RECORD
