Metadata-Version: 2.4
Name: distil-trainer
Version: 0.1.27
Summary: A comprehensive knowledge distillation training framework for transformer models
Project-URL: Homepage, https://github.com/malibayram/distil-trainer
Project-URL: Repository, https://github.com/malibayram/distil-trainer
Project-URL: Issues, https://github.com/malibayram/distil-trainer/issues
Author-email: Ali Bayram <malibayram20@gmail.com>
License: MIT
License-File: LICENSE
Keywords: deep-learning,distillation,knowledge-distillation,model-compression,nlp,pruning,pytorch,sentence-transformers,transformers
Classifier: Development Status :: 3 - Alpha
Classifier: Intended Audience :: Developers
Classifier: Intended Audience :: Science/Research
Classifier: License :: OSI Approved :: MIT License
Classifier: Operating System :: OS Independent
Classifier: Programming Language :: Python :: 3
Classifier: Programming Language :: Python :: 3.10
Classifier: Programming Language :: Python :: 3.11
Classifier: Programming Language :: Python :: 3.12
Classifier: Topic :: Scientific/Engineering :: Artificial Intelligence
Classifier: Topic :: Software Development :: Libraries :: Python Modules
Requires-Python: >=3.10
Requires-Dist: accelerate>=0.24.0
Requires-Dist: datasets>=2.14.0
Requires-Dist: numpy>=1.24.0
Requires-Dist: pandas>=2.0.0
Requires-Dist: protobuf
Requires-Dist: scikit-learn>=1.0.0
Requires-Dist: sentence-transformers>=2.2.0
Requires-Dist: torch>=2.0.0
Requires-Dist: tqdm>=4.65.0
Requires-Dist: transformers>=4.35.0
Provides-Extra: all
Requires-Dist: bitsandbytes>=0.41.0; extra == 'all'
Requires-Dist: mteb>=1.0.0; extra == 'all'
Requires-Dist: onnx>=1.14.0; extra == 'all'
Requires-Dist: onnxruntime>=1.16.0; extra == 'all'
Requires-Dist: peft>=0.6.0; extra == 'all'
Requires-Dist: tensorboard>=2.14.0; extra == 'all'
Requires-Dist: wandb>=0.15.0; extra == 'all'
Provides-Extra: dev
Requires-Dist: black>=23.0.0; extra == 'dev'
Requires-Dist: mypy>=1.0.0; extra == 'dev'
Requires-Dist: pre-commit>=3.0.0; extra == 'dev'
Requires-Dist: pytest-cov>=4.0.0; extra == 'dev'
Requires-Dist: pytest>=7.0.0; extra == 'dev'
Requires-Dist: ruff>=0.1.0; extra == 'dev'
Provides-Extra: evaluation
Requires-Dist: mteb>=1.0.0; extra == 'evaluation'
Provides-Extra: export
Requires-Dist: onnx>=1.14.0; extra == 'export'
Requires-Dist: onnxruntime>=1.16.0; extra == 'export'
Provides-Extra: peft
Requires-Dist: peft>=0.6.0; extra == 'peft'
Provides-Extra: quantization
Requires-Dist: bitsandbytes>=0.41.0; extra == 'quantization'
Provides-Extra: tracking
Requires-Dist: tensorboard>=2.14.0; extra == 'tracking'
Requires-Dist: wandb>=0.15.0; extra == 'tracking'
